{"id":"a47010c2eb0462e39a23a9a2874dc8b1","source_id_to_path":{"0":"contracts/NFT.sol","1":"contracts/TestCalls.sol","2":"contracts/Token.sol","3":"dependencies/@openzeppelin-contracts-5.0.2/interfaces/draft-IERC6093.sol","4":"dependencies/@openzeppelin-contracts-5.0.2/token/ERC20/ERC20.sol","5":"dependencies/@openzeppelin-contracts-5.0.2/token/ERC20/IERC20.sol","6":"dependencies/@openzeppelin-contracts-5.0.2/token/ERC20/extensions/IERC20Metadata.sol","7":"dependencies/@openzeppelin-contracts-5.0.2/token/ERC721/ERC721.sol","8":"dependencies/@openzeppelin-contracts-5.0.2/token/ERC721/IERC721.sol","9":"dependencies/@openzeppelin-contracts-5.0.2/token/ERC721/IERC721Receiver.sol","10":"dependencies/@openzeppelin-contracts-5.0.2/token/ERC721/extensions/ERC721Enumerable.sol","11":"dependencies/@openzeppelin-contracts-5.0.2/token/ERC721/extensions/IERC721Enumerable.sol","12":"dependencies/@openzeppelin-contracts-5.0.2/token/ERC721/extensions/IERC721Metadata.sol","13":"dependencies/@openzeppelin-contracts-5.0.2/utils/Base64.sol","14":"dependencies/@openzeppelin-contracts-5.0.2/utils/Context.sol","15":"dependencies/@openzeppelin-contracts-5.0.2/utils/Strings.sol","16":"dependencies/@openzeppelin-contracts-5.0.2/utils/introspection/ERC165.sol","17":"dependencies/@openzeppelin-contracts-5.0.2/utils/introspection/IERC165.sol","18":"dependencies/@openzeppelin-contracts-5.0.2/utils/math/Math.sol","19":"dependencies/@openzeppelin-contracts-5.0.2/utils/math/SignedMath.sol","20":"dependencies/forge-std-1.9.4/src/Base.sol","21":"dependencies/forge-std-1.9.4/src/Script.sol","22":"dependencies/forge-std-1.9.4/src/StdChains.sol","23":"dependencies/forge-std-1.9.4/src/StdCheats.sol","24":"dependencies/forge-std-1.9.4/src/StdJson.sol","25":"dependencies/forge-std-1.9.4/src/StdMath.sol","26":"dependencies/forge-std-1.9.4/src/StdStorage.sol","27":"dependencies/forge-std-1.9.4/src/StdStyle.sol","28":"dependencies/forge-std-1.9.4/src/StdUtils.sol","29":"dependencies/forge-std-1.9.4/src/Vm.sol","30":"dependencies/forge-std-1.9.4/src/console.sol","31":"dependencies/forge-std-1.9.4/src/console2.sol","32":"dependencies/forge-std-1.9.4/src/interfaces/IERC165.sol","33":"dependencies/forge-std-1.9.4/src/interfaces/IERC20.sol","34":"dependencies/forge-std-1.9.4/src/interfaces/IERC721.sol","35":"dependencies/forge-std-1.9.4/src/interfaces/IMulticall3.sol","36":"dependencies/forge-std-1.9.4/src/mocks/MockERC20.sol","37":"dependencies/forge-std-1.9.4/src/mocks/MockERC721.sol","38":"dependencies/forge-std-1.9.4/src/safeconsole.sol","39":"script/DevDeploy.s.sol"},"language":"Solidity"}